{
  "name": "Israel",
  "region": "Unknown",
  "scores": {
    "autonomy": 69.50328398007983,
    "autonomy_confidence": 1.0,
    "resilience": 98.6168918198394,
    "resilience_confidence": 0.9,
    "sustainability": 75.53512819596443,
    "sustainability_confidence": 0.9,
    "effectiveness": 0.3786154401484682,
    "effectiveness_confidence": 1.0
  },
  "industries": {
    "communications": {
      "scores": {
        "autonomy": null,
        "autonomy_confidence": 0,
        "resilience": 97.0,
        "resilience_confidence": 0.9,
        "sustainability": 38.859163798668504,
        "sustainability_confidence": 0.9,
        "effectiveness": null,
        "effectiveness_confidence": 0
      },
      "pillars": {},
      "indicators": [
        {
          "key": "ITU_MOB_BB_COVERAGE",
          "description": "Population coverage, by mobile network technology",
          "value": 97.0,
          "weight": 1,
          "source": "ITU",
          "year": 2023,
          "pillar": "resilience"
        },
        {
          "key": "IT.NET.BBND.P2",
          "description": "Fixed-broadband subscriptions (per 100 people)",
          "value": 38.859163798668504,
          "weight": 1,
          "source": "World Bank",
          "year": 2023,
          "pillar": "sustainability"
        }
      ]
    },
    "defence": {
      "scores": {
        "autonomy": 85.61896164606873,
        "autonomy_confidence": 0.9,
        "resilience": 0.643272740414152,
        "resilience_confidence": 0.6,
        "sustainability": 75.53512819596443,
        "sustainability_confidence": 0.9,
        "effectiveness": 26.506334816930448,
        "effectiveness_confidence": 0.9
      },
      "pillars": {},
      "indicators": [
        {
          "key": "MS.MIL.XPND.GD.ZS",
          "description": "Military expenditure (% of GDP)",
          "value": 85.61896164606873,
          "weight": 1,
          "source": "World Bank",
          "year": 2023,
          "pillar": "autonomy"
        },
        {
          "key": "MS.MIL.TOTL.P1",
          "description": "Armed forces personnel, total",
          "value": 0.643272740414152,
          "weight": 1,
          "source": "World Bank",
          "year": 2020,
          "pillar": "resilience"
        },
        {
          "key": "MS.MIL.XPND.ZS",
          "description": "Military expenditure (% of central government expenditure)",
          "value": 75.53512819596443,
          "weight": 1,
          "source": "World Bank",
          "year": 2023,
          "pillar": "sustainability"
        },
        {
          "key": "MS.MIL.XPND.CD",
          "description": "Military expenditure (current USD)",
          "value": 1.1521956772184327,
          "weight": 1,
          "source": "World Bank",
          "year": 2023,
          "pillar": "effectiveness"
        },
        {
          "key": "MS.MIL.XPND.PC.CD",
          "description": "Military expenditure per capita (current USD)",
          "value": 51.860473956642466,
          "weight": 1,
          "source": "Derived from World Bank",
          "year": 2023,
          "pillar": "effectiveness"
        }
      ]
    },
    "energy": {
      "scores": {
        "autonomy": 28.320958963384925,
        "autonomy_confidence": 0.9,
        "resilience": 93.60148007665929,
        "resilience_confidence": 0.9,
        "sustainability": 6.438213914849429,
        "sustainability_confidence": 0.7,
        "effectiveness": 100.0,
        "effectiveness_confidence": 0.9
      },
      "pillars": {},
      "indicators": [
        {
          "key": "EG.IMP.CONS.ZS",
          "description": "Energy imports, net (% of energy use)",
          "value": 28.320958963384925,
          "weight": 1,
          "source": "World Bank",
          "year": 2023,
          "pillar": "autonomy"
        },
        {
          "key": "EG.ELC.LOSS.ZS",
          "description": "Electric power transmission and distribution losses (% of output)",
          "value": 93.60148007665929,
          "weight": 1,
          "source": "World Bank",
          "year": 2023,
          "pillar": "resilience"
        },
        {
          "key": "EG.FEC.RNEW.ZS",
          "description": "Renewable energy consumption (% of total final energy consumption)",
          "value": 6.438213914849429,
          "weight": 1,
          "source": "World Bank",
          "year": 2021,
          "pillar": "sustainability"
        },
        {
          "key": "EG.ELC.ACCS.ZS",
          "description": "Access to electricity (% of population)",
          "value": 100.0,
          "weight": 1,
          "source": "World Bank",
          "year": 2023,
          "pillar": "effectiveness"
        }
      ]
    },
    "finance": {
      "scores": {
        "autonomy": 24.27244148067284,
        "autonomy_confidence": 0.9,
        "resilience": 98.6168918198394,
        "resilience_confidence": 0.9,
        "sustainability": 92.49230115748117,
        "sustainability_confidence": 0.7,
        "effectiveness": 9.946352973866755,
        "effectiveness_confidence": 0.9
      },
      "pillars": {},
      "indicators": [
        {
          "key": "FS.AST.PRVT.GD.ZS",
          "description": "Domestic credit to private sector (% of GDP)",
          "value": 24.27244148067284,
          "weight": 1,
          "source": "World Bank",
          "year": 2023,
          "pillar": "autonomy"
        },
        {
          "key": "FB.AST.NPER.ZS",
          "description": "Bank nonperforming loans to total gross loans (%)",
          "value": 98.6168918198394,
          "weight": 1,
          "source": "World Bank",
          "year": 2023,
          "pillar": "resilience"
        },
        {
          "key": "FX.OWN.TOTL.ZS",
          "description": "Account ownership at a financial institution or with a mobile-money-service provider (% of population ages 15+)",
          "value": 92.49230115748117,
          "weight": 1,
          "source": "World Bank",
          "year": 2021,
          "pillar": "sustainability"
        },
        {
          "key": "FB.CBK.BRCH.P5",
          "description": "Commercial bank branches (per 100,000 adults)",
          "value": 9.946352973866755,
          "weight": 1,
          "source": "World Bank",
          "year": 2023,
          "pillar": "effectiveness"
        }
      ]
    },
    "food_and_agriculture": {
      "scores": {
        "autonomy": null,
        "autonomy_confidence": 0,
        "resilience": null,
        "resilience_confidence": 0,
        "sustainability": null,
        "sustainability_confidence": 0,
        "effectiveness": null,
        "effectiveness_confidence": 0
      },
      "pillars": {},
      "indicators": []
    },
    "healthcare": {
      "scores": {
        "autonomy": 39.653361344537814,
        "autonomy_confidence": 0.9,
        "resilience": 57.27559982330915,
        "resilience_confidence": 0.7,
        "sustainability": 33.903122522699555,
        "sustainability_confidence": 0.8,
        "effectiveness": 98.98989898989899,
        "effectiveness_confidence": 0.9
      },
      "pillars": {},
      "indicators": [
        {
          "key": "HWF_0001",
          "description": "Physicians per 1,000 population",
          "value": 39.653361344537814,
          "weight": 1,
          "source": "WHO",
          "year": 2023,
          "pillar": "autonomy"
        },
        {
          "key": "SH.MED.BEDS.ZS",
          "description": "Hospital beds (per 1,000 people)",
          "value": 22.738001573564123,
          "weight": 1,
          "source": "World Bank",
          "year": 2021,
          "pillar": "resilience"
        },
        {
          "key": "UHC_INDEX_REPORTED",
          "description": "UHC Service Coverage Index (0-100)",
          "value": 91.81319807305418,
          "weight": 1,
          "source": "WHO GHO",
          "year": 2021,
          "pillar": "resilience"
        },
        {
          "key": "SH.XPD.CHEX.PC.CD",
          "description": "Current health expenditure per capita (current US$)",
          "value": 33.903122522699555,
          "weight": 1,
          "source": "World Bank",
          "year": 2022,
          "pillar": "sustainability"
        },
        {
          "key": "SH.IMM.IDPT",
          "description": "Immunization, DPT (% of children ages 12-23 months)",
          "value": 98.98989898989899,
          "weight": 1,
          "source": "World Bank",
          "year": 2023,
          "pillar": "effectiveness"
        }
      ]
    },
    "transport": {
      "scores": {
        "autonomy": 85.758285991999,
        "autonomy_confidence": 0.9,
        "resilience": 70.83333333333334,
        "resilience_confidence": 0.8,
        "sustainability": null,
        "sustainability_confidence": 0,
        "effectiveness": 77.27272727272727,
        "effectiveness_confidence": 0.8
      },
      "pillars": {},
      "indicators": [
        {
          "key": "EG.USE.PCAP.KG.OE",
          "description": "Energy use (kg of oil equivalent per capita)",
          "value": 85.758285991999,
          "weight": 1,
          "source": "World Bank",
          "year": 2023,
          "pillar": "autonomy"
        },
        {
          "key": "LP.LPI.OVRL.XQ",
          "description": "Logistics performance index: Overall",
          "value": 70.83333333333334,
          "weight": 1,
          "source": "World Bank",
          "year": 2022,
          "pillar": "resilience"
        },
        {
          "key": "LP.LPI.TIME.XQ",
          "description": "Logistics performance index: Timeliness of shipments",
          "value": 77.27272727272727,
          "weight": 1,
          "source": "World Bank",
          "year": 2022,
          "pillar": "effectiveness"
        }
      ]
    },
    "water": {
      "scores": {
        "autonomy": 0.016974188676687152,
        "autonomy_confidence": 0.7,
        "resilience": 99.37777237222085,
        "resilience_confidence": 0.8,
        "sustainability": 96.57258903750632,
        "sustainability_confidence": 0.7,
        "effectiveness": 96.44426,
        "effectiveness_confidence": 0.8
      },
      "pillars": {},
      "indicators": [
        {
          "key": "ER.H2O.INTR.PC",
          "description": "Renewable internal freshwater resources per capita (cubic meters)",
          "value": 0.016974188676687152,
          "weight": 1,
          "source": "World Bank",
          "year": 2021,
          "pillar": "autonomy"
        },
        {
          "key": "WSH_WATER_SAFELY_MANAGED",
          "description": "Population with access to safely managed drinking water (%)",
          "value": 99.37777237222085,
          "weight": 1,
          "source": "WHO",
          "year": 2022,
          "pillar": "resilience"
        },
        {
          "key": "ER.H2O.FWST.ZS",
          "description": "Level of water stress: freshwater withdrawal as a proportion of available freshwater resources (%)",
          "value": 96.57258903750632,
          "weight": 1,
          "source": "World Bank",
          "year": 2021,
          "pillar": "sustainability"
        },
        {
          "key": "WSH_SANITATION_SAFELY_MANAGED",
          "description": "Population with access to safely managed sanitation services (%)",
          "value": 96.44426,
          "weight": 1,
          "source": "WHO",
          "year": 2022,
          "pillar": "effectiveness"
        }
      ]
    },
    "waste_management": {
      "scores": {
        "autonomy": null,
        "autonomy_confidence": 0,
        "resilience": null,
        "resilience_confidence": 0,
        "sustainability": null,
        "sustainability_confidence": 0,
        "effectiveness": null,
        "effectiveness_confidence": 0
      },
      "pillars": {},
      "indicators": []
    },
    "emergency_services": {
      "scores": {
        "autonomy": null,
        "autonomy_confidence": 0,
        "resilience": null,
        "resilience_confidence": 0,
        "sustainability": null,
        "sustainability_confidence": 0,
        "effectiveness": null,
        "effectiveness_confidence": 0
      },
      "pillars": {},
      "indicators": []
    },
    "information_technology": {
      "scores": {
        "autonomy": 69.50328398007983,
        "autonomy_confidence": 1.0,
        "resilience": null,
        "resilience_confidence": 0,
        "sustainability": 100.0,
        "sustainability_confidence": 0.8,
        "effectiveness": 0.3786154401484682,
        "effectiveness_confidence": 1.0
      },
      "pillars": {},
      "indicators": [
        {
          "key": "BX.GSR.CCIS.ZS",
          "description": "ICT service exports (% of service exports, BoP)",
          "value": 100.0,
          "weight": 1,
          "source": "World Bank",
          "year": 2024,
          "pillar": "autonomy"
        },
        {
          "key": "TX.VAL.TECH.MF.ZS",
          "description": "High-technology exports (% of manufactured exports)",
          "value": 39.00656796015964,
          "weight": 1,
          "source": "World Bank",
          "year": 2024,
          "pillar": "autonomy"
        },
        {
          "key": "GB.XPD.RSDV.GD.ZS",
          "description": "Research and development expenditure (% of GDP)",
          "value": 100.0,
          "weight": 1,
          "source": "World Bank",
          "year": 2022,
          "pillar": "sustainability"
        },
        {
          "key": "IT.NET.SECR.P6",
          "description": "Secure Internet servers (per 1 million people)",
          "value": 0.3786154401484682,
          "weight": 1,
          "source": "World Bank",
          "year": 2024,
          "pillar": "effectiveness"
        }
      ]
    }
  },
  "historical_scores": [
    {
      "scores": {
        "overall": 54.18469346843938,
        "resilience": 99.40314275059531,
        "sustainability": 97.39265001680778,
        "autonomy": 0.01756924141425955,
        "effectiveness": 91.75066,
        "context": 0.11108206845482638
      },
      "industries": {
        "communications": {
          "scores": {
            "overall": 65.91545445064469,
            "resilience": 94.0,
            "sustainability": 37.830908901289376
          },
          "pillars": {
            "resilience": {
              "scores": {
                "overall": 94.0
              }
            },
            "sustainability": {
              "scores": {
                "overall": 37.830908901289376
              }
            }
          },
          "indicators": [
            {
              "key": "IT.NET.BBND.P2",
              "description": "Fixed-broadband subscriptions (per 100 people)",
              "value": 37.830908901289376,
              "weight": 1,
              "source": "World Bank",
              "year": 2019,
              "pillar": "sustainability"
            },
            {
              "key": "ITU_MOB_BB_COVERAGE",
              "description": "Population coverage, by mobile network technology",
              "value": 94.0,
              "weight": 1,
              "source": "ITU",
              "year": 2019,
              "pillar": "resilience"
            }
          ]
        },
        "defence": {
          "scores": {
            "overall": 49.00209763140229,
            "autonomy": 86.24449010038111,
            "effectiveness": 31.059730323673588,
            "resilience": 0.643272740414152,
            "sustainability": 78.06089736114032
          },
          "pillars": {
            "autonomy": {
              "scores": {
                "overall": 86.24449010038111
              }
            },
            "effectiveness": {
              "scores": {
                "overall": 31.059730323673588
              }
            },
            "resilience": {
              "scores": {
                "overall": 0.643272740414152
              }
            },
            "sustainability": {
              "scores": {
                "overall": 78.06089736114032
              }
            }
          },
          "indicators": [
            {
              "key": "MS.MIL.TOTL.P1",
              "description": "Armed forces personnel, total",
              "value": 0.643272740414152,
              "weight": 1,
              "source": "World Bank",
              "year": 2019,
              "pillar": "resilience"
            },
            {
              "key": "MS.MIL.XPND.CD",
              "description": "Military expenditure (current USD)",
              "value": 0.852218996008418,
              "weight": 1,
              "source": "World Bank",
              "year": 2019,
              "pillar": "effectiveness"
            },
            {
              "key": "MS.MIL.XPND.GD.ZS",
              "description": "Military expenditure (% of GDP)",
              "value": 86.24449010038111,
              "weight": 1,
              "source": "World Bank",
              "year": 2019,
              "pillar": "autonomy"
            },
            {
              "key": "MS.MIL.XPND.PC.CD",
              "description": "Military expenditure per capita (current USD)",
              "value": 61.26724165133876,
              "weight": 1,
              "source": "Derived from World Bank",
              "year": 2019,
              "pillar": "effectiveness"
            },
            {
              "key": "MS.MIL.XPND.ZS",
              "description": "Military expenditure (% of central government expenditure)",
              "value": 78.06089736114032,
              "weight": 1,
              "source": "World Bank",
              "year": 2019,
              "pillar": "sustainability"
            }
          ]
        },
        "energy": {
          "scores": {
            "overall": 55.97201123243583,
            "autonomy": 24.409438133951184,
            "effectiveness": 100.0,
            "resilience": 94.80570959953047,
            "sustainability": 4.672897196261682
          },
          "pillars": {
            "autonomy": {
              "scores": {
                "overall": 24.409438133951184
              }
            },
            "effectiveness": {
              "scores": {
                "overall": 100.0
              }
            },
            "resilience": {
              "scores": {
                "overall": 94.80570959953047
              }
            },
            "sustainability": {
              "scores": {
                "overall": 4.672897196261682
              }
            }
          },
          "indicators": [
            {
              "key": "EG.ELC.ACCS.ZS",
              "description": "Access to electricity (% of population)",
              "value": 100.0,
              "weight": 1,
              "source": "World Bank",
              "year": 2019,
              "pillar": "effectiveness"
            },
            {
              "key": "EG.ELC.LOSS.ZS",
              "description": "Electric power transmission and distribution losses (% of output)",
              "value": 94.80570959953047,
              "weight": 1,
              "source": "World Bank",
              "year": 2019,
              "pillar": "resilience"
            },
            {
              "key": "EG.FEC.RNEW.ZS",
              "description": "Renewable energy consumption (% of total final energy consumption)",
              "value": 4.672897196261682,
              "weight": 1,
              "source": "World Bank",
              "year": 2019,
              "pillar": "sustainability"
            },
            {
              "key": "EG.IMP.CONS.ZS",
              "description": "Energy imports, net (% of energy use)",
              "value": 24.409438133951184,
              "weight": 1,
              "source": "World Bank",
              "year": 2019,
              "pillar": "autonomy"
            }
          ]
        },
        "finance": {
          "scores": {
            "overall": 44.10045354767349,
            "autonomy": 22.491454486290323,
            "effectiveness": 11.875863024026142,
            "resilience": 97.93404313270402
          },
          "pillars": {
            "autonomy": {
              "scores": {
                "overall": 22.491454486290323
              }
            },
            "effectiveness": {
              "scores": {
                "overall": 11.875863024026142
              }
            },
            "resilience": {
              "scores": {
                "overall": 97.93404313270402
              }
            }
          },
          "indicators": [
            {
              "key": "FB.AST.NPER.ZS",
              "description": "Bank nonperforming loans to total gross loans (%)",
              "value": 97.93404313270402,
              "weight": 1,
              "source": "World Bank",
              "year": 2019,
              "pillar": "resilience"
            },
            {
              "key": "FB.CBK.BRCH.P5",
              "description": "Commercial bank branches (per 100,000 adults)",
              "value": 11.875863024026142,
              "weight": 1,
              "source": "World Bank",
              "year": 2019,
              "pillar": "effectiveness"
            },
            {
              "key": "FS.AST.PRVT.GD.ZS",
              "description": "Domestic credit to private sector (% of GDP)",
              "value": 22.491454486290323,
              "weight": 1,
              "source": "World Bank",
              "year": 2019,
              "pillar": "autonomy"
            }
          ]
        },
        "general": {
          "scores": {
            "overall": 0.11108206845482638,
            "context": 0.11108206845482638
          },
          "pillars": {
            "context": {
              "scores": {
                "overall": 0.11108206845482638
              }
            }
          },
          "indicators": [
            {
              "key": "SP.POP.TOTL",
              "description": "Population, total",
              "value": 0.11108206845482638,
              "weight": 1,
              "source": "World Bank",
              "year": 2019,
              "pillar": "context"
            }
          ]
        },
        "healthcare": {
          "scores": {
            "overall": 53.706862800791626,
            "autonomy": 36.754201680672274,
            "effectiveness": 93.81214489263033,
            "resilience": 57.51163444171985,
            "sustainability": 26.74947018814404
          },
          "pillars": {
            "autonomy": {
              "scores": {
                "overall": 36.754201680672274
              }
            },
            "effectiveness": {
              "scores": {
                "overall": 93.81214489263033
              }
            },
            "resilience": {
              "scores": {
                "overall": 57.51163444171985
              }
            },
            "sustainability": {
              "scores": {
                "overall": 26.74947018814404
              }
            }
          },
          "indicators": [
            {
              "key": "HWF_0001",
              "description": "Physicians per 1,000 population",
              "value": 36.754201680672274,
              "weight": 1,
              "source": "WHO",
              "year": 2019,
              "pillar": "autonomy"
            },
            {
              "key": "SH.IMM.IDPT",
              "description": "Immunization, DPT (% of children ages 12-23 months)",
              "value": 98.98989898989899,
              "weight": 1,
              "source": "World Bank",
              "year": 2019,
              "pillar": "effectiveness"
            },
            {
              "key": "SH.MED.BEDS.ZS",
              "description": "Hospital beds (per 1,000 people)",
              "value": 23.21007081038552,
              "weight": 1,
              "source": "World Bank",
              "year": 2019,
              "pillar": "resilience"
            },
            {
              "key": "SH.XPD.CHEX.PC.CD",
              "description": "Current health expenditure per capita (current US$)",
              "value": 26.74947018814404,
              "weight": 1,
              "source": "World Bank",
              "year": 2019,
              "pillar": "sustainability"
            },
            {
              "key": "UHC_INDEX_REPORTED",
              "description": "UHC Service Coverage Index (0-100)",
              "value": 91.81319807305418,
              "weight": 1,
              "source": "WHO GHO",
              "year": 2019,
              "pillar": "resilience"
            },
            {
              "key": "WHOSIS_000002",
              "description": "Healthy life expectancy (HALE) at birth (years)",
              "value": 88.63439079536167,
              "weight": 1,
              "source": "WHO",
              "year": 2019,
              "pillar": "effectiveness"
            }
          ]
        },
        "information_technology": {
          "scores": {
            "overall": 60.794381048393575,
            "autonomy": 50.721046538713495,
            "effectiveness": 43.14157908444663,
            "sustainability": 88.52051752202058
          },
          "pillars": {
            "autonomy": {
              "scores": {
                "overall": 50.721046538713495
              }
            },
            "effectiveness": {
              "scores": {
                "overall": 43.14157908444663
              }
            },
            "sustainability": {
              "scores": {
                "overall": 88.52051752202058
              }
            }
          },
          "indicators": [
            {
              "key": "BX.GSR.CCIS.ZS",
              "description": "ICT service exports (% of service exports, BoP)",
              "value": 77.29216180756285,
              "weight": 1,
              "source": "World Bank",
              "year": 2019,
              "pillar": "autonomy"
            },
            {
              "key": "GB.XPD.RSDV.GD.ZS",
              "description": "Research and development expenditure (% of GDP)",
              "value": 88.52051752202058,
              "weight": 1,
              "source": "World Bank",
              "year": 2019,
              "pillar": "sustainability"
            },
            {
              "key": "IT.NET.SECR.P6",
              "description": "Secure Internet servers (per 1 million people)",
              "value": 0.34066615611370643,
              "weight": 1,
              "source": "World Bank",
              "year": 2019,
              "pillar": "effectiveness"
            },
            {
              "key": "IT.NET.USER.ZS",
              "description": "Individuals using the Internet (% of population)",
              "value": 85.94249201277955,
              "weight": 1,
              "source": "World Bank",
              "year": 2019,
              "pillar": "effectiveness"
            },
            {
              "key": "TX.VAL.TECH.MF.ZS",
              "description": "High-technology exports (% of manufactured exports)",
              "value": 24.149931269864148,
              "weight": 1,
              "source": "World Bank",
              "year": 2019,
              "pillar": "autonomy"
            }
          ]
        },
        "transport": {
          "scores": {
            "overall": 85.91889293395371,
            "autonomy": 85.91889293395371
          },
          "pillars": {
            "autonomy": {
              "scores": {
                "overall": 85.91889293395371
              }
            }
          },
          "indicators": [
            {
              "key": "EG.USE.PCAP.KG.OE",
              "description": "Energy use (kg of oil equivalent per capita)",
              "value": 85.91889293395371,
              "weight": 1,
              "source": "World Bank",
              "year": 2019,
              "pillar": "autonomy"
            }
          ]
        },
        "water": {
          "scores": {
            "overall": 72.14100550220434,
            "autonomy": 0.01756924141425955,
            "effectiveness": 91.75066,
            "resilience": 99.40314275059531,
            "sustainability": 97.39265001680778
          },
          "pillars": {
            "autonomy": {
              "scores": {
                "overall": 0.01756924141425955
              }
            },
            "effectiveness": {
              "scores": {
                "overall": 91.75066
              }
            },
            "resilience": {
              "scores": {
                "overall": 99.40314275059531
              }
            },
            "sustainability": {
              "scores": {
                "overall": 97.39265001680778
              }
            }
          },
          "indicators": [
            {
              "key": "ER.H2O.FWST.ZS",
              "description": "Level of water stress: freshwater withdrawal as a proportion of available freshwater resources (%)",
              "value": 97.39265001680778,
              "weight": 1,
              "source": "World Bank",
              "year": 2019,
              "pillar": "sustainability"
            },
            {
              "key": "ER.H2O.INTR.PC",
              "description": "Renewable internal freshwater resources per capita (cubic meters)",
              "value": 0.01756924141425955,
              "weight": 1,
              "source": "World Bank",
              "year": 2019,
              "pillar": "autonomy"
            },
            {
              "key": "WSH_SANITATION_SAFELY_MANAGED",
              "description": "Population with access to safely managed sanitation services (%)",
              "value": 91.75066,
              "weight": 1,
              "source": "WHO",
              "year": 2019,
              "pillar": "effectiveness"
            },
            {
              "key": "WSH_WATER_SAFELY_MANAGED",
              "description": "Population with access to safely managed drinking water (%)",
              "value": 99.40314275059531,
              "weight": 1,
              "source": "WHO",
              "year": 2019,
              "pillar": "resilience"
            }
          ]
        }
      }
    },
    {
      "scores": {
        "overall": 54.49124462130639,
        "resilience": 99.4973770205084,
        "sustainability": 97.14170239472651,
        "autonomy": 0.01726209284377879,
        "effectiveness": 94.9294,
        "context": 0.11306068641118594
      },
      "industries": {
        "communications": {
          "scores": {
            "overall": 68.01677696413319,
            "resilience": 97.0,
            "sustainability": 39.03355392826638
          },
          "pillars": {
            "resilience": {
              "scores": {
                "overall": 97.0
              }
            },
            "sustainability": {
              "scores": {
                "overall": 39.03355392826638
              }
            }
          },
          "indicators": [
            {
              "key": "IT.NET.BBND.P2",
              "description": "Fixed-broadband subscriptions (per 100 people)",
              "value": 39.03355392826638,
              "weight": 1,
              "source": "World Bank",
              "year": 2020,
              "pillar": "sustainability"
            },
            {
              "key": "ITU_MOB_BB_COVERAGE",
              "description": "Population coverage, by mobile network technology",
              "value": 97.0,
              "weight": 1,
              "source": "ITU",
              "year": 2020,
              "pillar": "resilience"
            }
          ]
        },
        "defence": {
          "scores": {
            "overall": 49.188729987749866,
            "autonomy": 85.68007351640696,
            "effectiveness": 30.047157918082657,
            "resilience": 0.643272740414152,
            "sustainability": 80.38441577609571
          },
          "pillars": {
            "autonomy": {
              "scores": {
                "overall": 85.68007351640696
              }
            },
            "effectiveness": {
              "scores": {
                "overall": 30.047157918082657
              }
            },
            "resilience": {
              "scores": {
                "overall": 0.643272740414152
              }
            },
            "sustainability": {
              "scores": {
                "overall": 80.38441577609571
              }
            }
          },
          "indicators": [
            {
              "key": "MS.MIL.TOTL.P1",
              "description": "Armed forces personnel, total",
              "value": 0.643272740414152,
              "weight": 1,
              "source": "World Bank",
              "year": 2020,
              "pillar": "resilience"
            },
            {
              "key": "MS.MIL.XPND.CD",
              "description": "Military expenditure (current USD)",
              "value": 0.9141201124887487,
              "weight": 1,
              "source": "World Bank",
              "year": 2020,
              "pillar": "effectiveness"
            },
            {
              "key": "MS.MIL.XPND.GD.ZS",
              "description": "Military expenditure (% of GDP)",
              "value": 85.68007351640696,
              "weight": 1,
              "source": "World Bank",
              "year": 2020,
              "pillar": "autonomy"
            },
            {
              "key": "MS.MIL.XPND.PC.CD",
              "description": "Military expenditure per capita (current USD)",
              "value": 59.18019572367657,
              "weight": 1,
              "source": "Derived from World Bank",
              "year": 2020,
              "pillar": "effectiveness"
            },
            {
              "key": "MS.MIL.XPND.ZS",
              "description": "Military expenditure (% of central government expenditure)",
              "value": 80.38441577609571,
              "weight": 1,
              "source": "World Bank",
              "year": 2020,
              "pillar": "sustainability"
            }
          ]
        },
        "energy": {
          "scores": {
            "overall": 56.52207370662976,
            "autonomy": 26.301163633942082,
            "effectiveness": 100.0,
            "resilience": 93.9719702372291,
            "sustainability": 5.815160955347871
          },
          "pillars": {
            "autonomy": {
              "scores": {
                "overall": 26.301163633942082
              }
            },
            "effectiveness": {
              "scores": {
                "overall": 100.0
              }
            },
            "resilience": {
              "scores": {
                "overall": 93.9719702372291
              }
            },
            "sustainability": {
              "scores": {
                "overall": 5.815160955347871
              }
            }
          },
          "indicators": [
            {
              "key": "EG.ELC.ACCS.ZS",
              "description": "Access to electricity (% of population)",
              "value": 100.0,
              "weight": 1,
              "source": "World Bank",
              "year": 2020,
              "pillar": "effectiveness"
            },
            {
              "key": "EG.ELC.LOSS.ZS",
              "description": "Electric power transmission and distribution losses (% of output)",
              "value": 93.9719702372291,
              "weight": 1,
              "source": "World Bank",
              "year": 2020,
              "pillar": "resilience"
            },
            {
              "key": "EG.FEC.RNEW.ZS",
              "description": "Renewable energy consumption (% of total final energy consumption)",
              "value": 5.815160955347871,
              "weight": 1,
              "source": "World Bank",
              "year": 2020,
              "pillar": "sustainability"
            },
            {
              "key": "EG.IMP.CONS.ZS",
              "description": "Energy imports, net (% of energy use)",
              "value": 26.301163633942082,
              "weight": 1,
              "source": "World Bank",
              "year": 2020,
              "pillar": "autonomy"
            }
          ]
        },
        "finance": {
          "scores": {
            "overall": 44.37166535934841,
            "autonomy": 23.716755676604745,
            "effectiveness": 11.442784426717267,
            "resilience": 97.95545597472324
          },
          "pillars": {
            "autonomy": {
              "scores": {
                "overall": 23.716755676604745
              }
            },
            "effectiveness": {
              "scores": {
                "overall": 11.442784426717267
              }
            },
            "resilience": {
              "scores": {
                "overall": 97.95545597472324
              }
            }
          },
          "indicators": [
            {
              "key": "FB.AST.NPER.ZS",
              "description": "Bank nonperforming loans to total gross loans (%)",
              "value": 97.95545597472324,
              "weight": 1,
              "source": "World Bank",
              "year": 2020,
              "pillar": "resilience"
            },
            {
              "key": "FB.CBK.BRCH.P5",
              "description": "Commercial bank branches (per 100,000 adults)",
              "value": 11.442784426717267,
              "weight": 1,
              "source": "World Bank",
              "year": 2020,
              "pillar": "effectiveness"
            },
            {
              "key": "FS.AST.PRVT.GD.ZS",
              "description": "Domestic credit to private sector (% of GDP)",
              "value": 23.716755676604745,
              "weight": 1,
              "source": "World Bank",
              "year": 2020,
              "pillar": "autonomy"
            }
          ]
        },
        "general": {
          "scores": {
            "overall": 0.11306068641118594,
            "context": 0.11306068641118594
          },
          "pillars": {
            "context": {
              "scores": {
                "overall": 0.11306068641118594
              }
            }
          },
          "indicators": [
            {
              "key": "SP.POP.TOTL",
              "description": "Population, total",
              "value": 0.11306068641118594,
              "weight": 1,
              "source": "World Bank",
              "year": 2020,
              "pillar": "context"
            }
          ]
        },
        "healthcare": {
          "scores": {
            "overall": 45.60887319447312,
            "autonomy": 37.23739495798319,
            "effectiveness": 93.36776460294612,
            "resilience": 22.816679779701023,
            "sustainability": 29.013653437262143
          },
          "pillars": {
            "autonomy": {
              "scores": {
                "overall": 37.23739495798319
              }
            },
            "effectiveness": {
              "scores": {
                "overall": 93.36776460294612
              }
            },
            "resilience": {
              "scores": {
                "overall": 22.816679779701023
              }
            },
            "sustainability": {
              "scores": {
                "overall": 29.013653437262143
              }
            }
          },
          "indicators": [
            {
              "key": "HWF_0001",
              "description": "Physicians per 1,000 population",
              "value": 37.23739495798319,
              "weight": 1,
              "source": "WHO",
              "year": 2020,
              "pillar": "autonomy"
            },
            {
              "key": "SH.IMM.IDPT",
              "description": "Immunization, DPT (% of children ages 12-23 months)",
              "value": 98.98989898989899,
              "weight": 1,
              "source": "World Bank",
              "year": 2020,
              "pillar": "effectiveness"
            },
            {
              "key": "SH.MED.BEDS.ZS",
              "description": "Hospital beds (per 1,000 people)",
              "value": 22.816679779701023,
              "weight": 1,
              "source": "World Bank",
              "year": 2020,
              "pillar": "resilience"
            },
            {
              "key": "SH.XPD.CHEX.PC.CD",
              "description": "Current health expenditure per capita (current US$)",
              "value": 29.013653437262143,
              "weight": 1,
              "source": "World Bank",
              "year": 2020,
              "pillar": "sustainability"
            },
            {
              "key": "WHOSIS_000002",
              "description": "Healthy life expectancy (HALE) at birth (years)",
              "value": 87.74563021599326,
              "weight": 1,
              "source": "WHO",
              "year": 2020,
              "pillar": "effectiveness"
            }
          ]
        },
        "information_technology": {
          "scores": {
            "overall": 68.0516525920819,
            "autonomy": 62.94719185932945,
            "effectiveness": 44.91772335112081,
            "sustainability": 96.29004256579543
          },
          "pillars": {
            "autonomy": {
              "scores": {
                "overall": 62.94719185932945
              }
            },
            "effectiveness": {
              "scores": {
                "overall": 44.91772335112081
              }
            },
            "sustainability": {
              "scores": {
                "overall": 96.29004256579543
              }
            }
          },
          "indicators": [
            {
              "key": "BX.GSR.CCIS.ZS",
              "description": "ICT service exports (% of service exports, BoP)",
              "value": 96.40447363716916,
              "weight": 1,
              "source": "World Bank",
              "year": 2020,
              "pillar": "autonomy"
            },
            {
              "key": "GB.XPD.RSDV.GD.ZS",
              "description": "Research and development expenditure (% of GDP)",
              "value": 96.29004256579543,
              "weight": 1,
              "source": "World Bank",
              "year": 2020,
              "pillar": "sustainability"
            },
            {
              "key": "IT.NET.SECR.P6",
              "description": "Secure Internet servers (per 1 million people)",
              "value": 0.37857769265695845,
              "weight": 1,
              "source": "World Bank",
              "year": 2020,
              "pillar": "effectiveness"
            },
            {
              "key": "IT.NET.USER.ZS",
              "description": "Individuals using the Internet (% of population)",
              "value": 89.45686900958466,
              "weight": 1,
              "source": "World Bank",
              "year": 2020,
              "pillar": "effectiveness"
            },
            {
              "key": "TX.VAL.TECH.MF.ZS",
              "description": "High-technology exports (% of manufactured exports)",
              "value": 29.489910081489747,
              "weight": 1,
              "source": "World Bank",
              "year": 2020,
              "pillar": "autonomy"
            }
          ]
        },
        "transport": {
          "scores": {
            "overall": 85.65193372391046,
            "autonomy": 85.65193372391046
          },
          "pillars": {
            "autonomy": {
              "scores": {
                "overall": 85.65193372391046
              }
            }
          },
          "indicators": [
            {
              "key": "EG.USE.PCAP.KG.OE",
              "description": "Energy use (kg of oil equivalent per capita)",
              "value": 85.65193372391046,
              "weight": 1,
              "source": "World Bank",
              "year": 2020,
              "pillar": "autonomy"
            }
          ]
        },
        "water": {
          "scores": {
            "overall": 72.89643537701967,
            "autonomy": 0.01726209284377879,
            "effectiveness": 94.9294,
            "resilience": 99.4973770205084,
            "sustainability": 97.14170239472651
          },
          "pillars": {
            "autonomy": {
              "scores": {
                "overall": 0.01726209284377879
              }
            },
            "effectiveness": {
              "scores": {
                "overall": 94.9294
              }
            },
            "resilience": {
              "scores": {
                "overall": 99.4973770205084
              }
            },
            "sustainability": {
              "scores": {
                "overall": 97.14170239472651
              }
            }
          },
          "indicators": [
            {
              "key": "ER.H2O.FWST.ZS",
              "description": "Level of water stress: freshwater withdrawal as a proportion of available freshwater resources (%)",
              "value": 97.14170239472651,
              "weight": 1,
              "source": "World Bank",
              "year": 2020,
              "pillar": "sustainability"
            },
            {
              "key": "ER.H2O.INTR.PC",
              "description": "Renewable internal freshwater resources per capita (cubic meters)",
              "value": 0.01726209284377879,
              "weight": 1,
              "source": "World Bank",
              "year": 2020,
              "pillar": "autonomy"
            },
            {
              "key": "WSH_SANITATION_SAFELY_MANAGED",
              "description": "Population with access to safely managed sanitation services (%)",
              "value": 94.9294,
              "weight": 1,
              "source": "WHO",
              "year": 2020,
              "pillar": "effectiveness"
            },
            {
              "key": "WSH_WATER_SAFELY_MANAGED",
              "description": "Population with access to safely managed drinking water (%)",
              "value": 99.4973770205084,
              "weight": 1,
              "source": "WHO",
              "year": 2020,
              "pillar": "resilience"
            }
          ]
        }
      }
    },
    {
      "scores": {
        "overall": 54.871220197896776,
        "resilience": 99.49054189479737,
        "sustainability": 96.57258903750632,
        "autonomy": 0.016974188676687152,
        "effectiveness": 95.49715,
        "context": 0.11498035113234673
      },
      "industries": {
        "communications": {
          "scores": {
            "overall": 34.60925257789799,
            "resilience": 30.0,
            "sustainability": 39.21850515579599
          },
          "pillars": {
            "resilience": {
              "scores": {
                "overall": 30.0
              }
            },
            "sustainability": {
              "scores": {
                "overall": 39.21850515579599
              }
            }
          },
          "indicators": [
            {
              "key": "IT.NET.BBND.P2",
              "description": "Fixed-broadband subscriptions (per 100 people)",
              "value": 39.21850515579599,
              "weight": 1,
              "source": "World Bank",
              "year": 2021,
              "pillar": "sustainability"
            },
            {
              "key": "ITU_MOB_BB_COVERAGE",
              "description": "Population coverage, by mobile network technology",
              "value": 30.0,
              "weight": 1,
              "source": "ITU",
              "year": 2021,
              "pillar": "resilience"
            }
          ]
        },
        "defence": {
          "scores": {
            "overall": 64.69879884137315,
            "autonomy": 86.5845151785183,
            "effectiveness": 28.118194358834756,
            "sustainability": 79.39368698676637
          },
          "pillars": {
            "autonomy": {
              "scores": {
                "overall": 86.5845151785183
              }
            },
            "effectiveness": {
              "scores": {
                "overall": 28.118194358834756
              }
            },
            "sustainability": {
              "scores": {
                "overall": 79.39368698676637
              }
            }
          },
          "indicators": [
            {
              "key": "MS.MIL.XPND.CD",
              "description": "Military expenditure (current USD)",
              "value": 1.0198935576718853,
              "weight": 1,
              "source": "World Bank",
              "year": 2021,
              "pillar": "effectiveness"
            },
            {
              "key": "MS.MIL.XPND.GD.ZS",
              "description": "Military expenditure (% of GDP)",
              "value": 86.5845151785183,
              "weight": 1,
              "source": "World Bank",
              "year": 2021,
              "pillar": "autonomy"
            },
            {
              "key": "MS.MIL.XPND.PC.CD",
              "description": "Military expenditure per capita (current USD)",
              "value": 55.21649515999763,
              "weight": 1,
              "source": "Derived from World Bank",
              "year": 2021,
              "pillar": "effectiveness"
            },
            {
              "key": "MS.MIL.XPND.ZS",
              "description": "Military expenditure (% of central government expenditure)",
              "value": 79.39368698676637,
              "weight": 1,
              "source": "World Bank",
              "year": 2021,
              "pillar": "sustainability"
            }
          ]
        },
        "energy": {
          "scores": {
            "overall": 56.835493164381894,
            "autonomy": 27.31013752880115,
            "effectiveness": 100.0,
            "resilience": 93.59362121387699,
            "sustainability": 6.438213914849429
          },
          "pillars": {
            "autonomy": {
              "scores": {
                "overall": 27.31013752880115
              }
            },
            "effectiveness": {
              "scores": {
                "overall": 100.0
              }
            },
            "resilience": {
              "scores": {
                "overall": 93.59362121387699
              }
            },
            "sustainability": {
              "scores": {
                "overall": 6.438213914849429
              }
            }
          },
          "indicators": [
            {
              "key": "EG.ELC.ACCS.ZS",
              "description": "Access to electricity (% of population)",
              "value": 100.0,
              "weight": 1,
              "source": "World Bank",
              "year": 2021,
              "pillar": "effectiveness"
            },
            {
              "key": "EG.ELC.LOSS.ZS",
              "description": "Electric power transmission and distribution losses (% of output)",
              "value": 93.59362121387699,
              "weight": 1,
              "source": "World Bank",
              "year": 2021,
              "pillar": "resilience"
            },
            {
              "key": "EG.FEC.RNEW.ZS",
              "description": "Renewable energy consumption (% of total final energy consumption)",
              "value": 6.438213914849429,
              "weight": 1,
              "source": "World Bank",
              "year": 2021,
              "pillar": "sustainability"
            },
            {
              "key": "EG.IMP.CONS.ZS",
              "description": "Energy imports, net (% of energy use)",
              "value": 27.31013752880115,
              "weight": 1,
              "source": "World Bank",
              "year": 2021,
              "pillar": "autonomy"
            }
          ]
        },
        "finance": {
          "scores": {
            "overall": 56.469366602488655,
            "autonomy": 24.143291845473566,
            "effectiveness": 10.754157699230252,
            "resilience": 98.48771570776964,
            "sustainability": 92.49230115748117
          },
          "pillars": {
            "autonomy": {
              "scores": {
                "overall": 24.143291845473566
              }
            },
            "effectiveness": {
              "scores": {
                "overall": 10.754157699230252
              }
            },
            "resilience": {
              "scores": {
                "overall": 98.48771570776964
              }
            },
            "sustainability": {
              "scores": {
                "overall": 92.49230115748117
              }
            }
          },
          "indicators": [
            {
              "key": "FB.AST.NPER.ZS",
              "description": "Bank nonperforming loans to total gross loans (%)",
              "value": 98.48771570776964,
              "weight": 1,
              "source": "World Bank",
              "year": 2021,
              "pillar": "resilience"
            },
            {
              "key": "FB.CBK.BRCH.P5",
              "description": "Commercial bank branches (per 100,000 adults)",
              "value": 10.754157699230252,
              "weight": 1,
              "source": "World Bank",
              "year": 2021,
              "pillar": "effectiveness"
            },
            {
              "key": "FS.AST.PRVT.GD.ZS",
              "description": "Domestic credit to private sector (% of GDP)",
              "value": 24.143291845473566,
              "weight": 1,
              "source": "World Bank",
              "year": 2021,
              "pillar": "autonomy"
            },
            {
              "key": "FX.OWN.TOTL.ZS",
              "description": "Account ownership at a financial institution or with a mobile-money-service provider (% of population ages 15+)",
              "value": 92.49230115748117,
              "weight": 1,
              "source": "World Bank",
              "year": 2021,
              "pillar": "sustainability"
            }
          ]
        },
        "general": {
          "scores": {
            "overall": 0.11498035113234673,
            "context": 0.11498035113234673
          },
          "pillars": {
            "context": {
              "scores": {
                "overall": 0.11498035113234673
              }
            }
          },
          "indicators": [
            {
              "key": "SP.POP.TOTL",
              "description": "Population, total",
              "value": 0.11498035113234673,
              "weight": 1,
              "source": "World Bank",
              "year": 2021,
              "pillar": "context"
            }
          ]
        },
        "healthcare": {
          "scores": {
            "overall": 55.37698066198139,
            "autonomy": 37.96218487394958,
            "effectiveness": 92.63476014966312,
            "resilience": 57.27559982330915,
            "sustainability": 33.63537780100372
          },
          "pillars": {
            "autonomy": {
              "scores": {
                "overall": 37.96218487394958
              }
            },
            "effectiveness": {
              "scores": {
                "overall": 92.63476014966312
              }
            },
            "resilience": {
              "scores": {
                "overall": 57.27559982330915
              }
            },
            "sustainability": {
              "scores": {
                "overall": 33.63537780100372
              }
            }
          },
          "indicators": [
            {
              "key": "HWF_0001",
              "description": "Physicians per 1,000 population",
              "value": 37.96218487394958,
              "weight": 1,
              "source": "WHO",
              "year": 2021,
              "pillar": "autonomy"
            },
            {
              "key": "SH.IMM.IDPT",
              "description": "Immunization, DPT (% of children ages 12-23 months)",
              "value": 98.98989898989899,
              "weight": 1,
              "source": "World Bank",
              "year": 2021,
              "pillar": "effectiveness"
            },
            {
              "key": "SH.MED.BEDS.ZS",
              "description": "Hospital beds (per 1,000 people)",
              "value": 22.738001573564123,
              "weight": 1,
              "source": "World Bank",
              "year": 2021,
              "pillar": "resilience"
            },
            {
              "key": "SH.XPD.CHEX.PC.CD",
              "description": "Current health expenditure per capita (current US$)",
              "value": 33.63537780100372,
              "weight": 1,
              "source": "World Bank",
              "year": 2021,
              "pillar": "sustainability"
            },
            {
              "key": "UHC_INDEX_REPORTED",
              "description": "UHC Service Coverage Index (0-100)",
              "value": 91.81319807305418,
              "weight": 1,
              "source": "WHO GHO",
              "year": 2021,
              "pillar": "resilience"
            },
            {
              "key": "WHOSIS_000002",
              "description": "Healthy life expectancy (HALE) at birth (years)",
              "value": 86.27962130942727,
              "weight": 1,
              "source": "WHO",
              "year": 2021,
              "pillar": "effectiveness"
            }
          ]
        },
        "information_technology": {
          "scores": {
            "overall": 67.0666154147702,
            "autonomy": 60.10965711454389,
            "effectiveness": 45.03448988753361,
            "sustainability": 96.0556992422331
          },
          "pillars": {
            "autonomy": {
              "scores": {
                "overall": 60.10965711454389
              }
            },
            "effectiveness": {
              "scores": {
                "overall": 45.03448988753361
              }
            },
            "sustainability": {
              "scores": {
                "overall": 96.0556992422331
              }
            }
          },
          "indicators": [
            {
              "key": "BX.GSR.CCIS.ZS",
              "description": "ICT service exports (% of service exports, BoP)",
              "value": 89.26730104272337,
              "weight": 1,
              "source": "World Bank",
              "year": 2021,
              "pillar": "autonomy"
            },
            {
              "key": "GB.XPD.RSDV.GD.ZS",
              "description": "Research and development expenditure (% of GDP)",
              "value": 96.0556992422331,
              "weight": 1,
              "source": "World Bank",
              "year": 2021,
              "pillar": "sustainability"
            },
            {
              "key": "IT.NET.SECR.P6",
              "description": "Secure Internet servers (per 1 million people)",
              "value": 0.3991182202216402,
              "weight": 1,
              "source": "World Bank",
              "year": 2021,
              "pillar": "effectiveness"
            },
            {
              "key": "IT.NET.USER.ZS",
              "description": "Individuals using the Internet (% of population)",
              "value": 89.66986155484558,
              "weight": 1,
              "source": "World Bank",
              "year": 2021,
              "pillar": "effectiveness"
            },
            {
              "key": "TX.VAL.TECH.MF.ZS",
              "description": "High-technology exports (% of manufactured exports)",
              "value": 30.952013186364415,
              "weight": 1,
              "source": "World Bank",
              "year": 2021,
              "pillar": "autonomy"
            }
          ]
        },
        "transport": {
          "scores": {
            "overall": 85.77518038680026,
            "autonomy": 85.77518038680026
          },
          "pillars": {
            "autonomy": {
              "scores": {
                "overall": 85.77518038680026
              }
            }
          },
          "indicators": [
            {
              "key": "EG.USE.PCAP.KG.OE",
              "description": "Energy use (kg of oil equivalent per capita)",
              "value": 85.77518038680026,
              "weight": 1,
              "source": "World Bank",
              "year": 2021,
              "pillar": "autonomy"
            }
          ]
        },
        "water": {
          "scores": {
            "overall": 72.8943137802451,
            "autonomy": 0.016974188676687152,
            "effectiveness": 95.49715,
            "resilience": 99.49054189479737,
            "sustainability": 96.57258903750632
          },
          "pillars": {
            "autonomy": {
              "scores": {
                "overall": 0.016974188676687152
              }
            },
            "effectiveness": {
              "scores": {
                "overall": 95.49715
              }
            },
            "resilience": {
              "scores": {
                "overall": 99.49054189479737
              }
            },
            "sustainability": {
              "scores": {
                "overall": 96.57258903750632
              }
            }
          },
          "indicators": [
            {
              "key": "ER.H2O.FWST.ZS",
              "description": "Level of water stress: freshwater withdrawal as a proportion of available freshwater resources (%)",
              "value": 96.57258903750632,
              "weight": 1,
              "source": "World Bank",
              "year": 2021,
              "pillar": "sustainability"
            },
            {
              "key": "ER.H2O.INTR.PC",
              "description": "Renewable internal freshwater resources per capita (cubic meters)",
              "value": 0.016974188676687152,
              "weight": 1,
              "source": "World Bank",
              "year": 2021,
              "pillar": "autonomy"
            },
            {
              "key": "WSH_SANITATION_SAFELY_MANAGED",
              "description": "Population with access to safely managed sanitation services (%)",
              "value": 95.49715,
              "weight": 1,
              "source": "WHO",
              "year": 2021,
              "pillar": "effectiveness"
            },
            {
              "key": "WSH_WATER_SAFELY_MANAGED",
              "description": "Population with access to safely managed drinking water (%)",
              "value": 99.49054189479737,
              "weight": 1,
              "source": "WHO",
              "year": 2021,
              "pillar": "resilience"
            }
          ]
        }
      }
    },
    {
      "scores": {
        "overall": 61.39100994364079,
        "resilience": 99.37777237222085,
        "sustainability": 100.0,
        "autonomy": 85.4025260540848,
        "effectiveness": 96.44426,
        "context": 0.11726601718870001
      },
      "industries": {
        "communications": {
          "scores": {
            "overall": 67.75268350897758,
            "resilience": 97.0,
            "sustainability": 38.50536701795518
          },
          "pillars": {
            "resilience": {
              "scores": {
                "overall": 97.0
              }
            },
            "sustainability": {
              "scores": {
                "overall": 38.50536701795518
              }
            }
          },
          "indicators": [
            {
              "key": "IT.NET.BBND.P2",
              "description": "Fixed-broadband subscriptions (per 100 people)",
              "value": 38.50536701795518,
              "weight": 1,
              "source": "World Bank",
              "year": 2022,
              "pillar": "sustainability"
            },
            {
              "key": "ITU_MOB_BB_COVERAGE",
              "description": "Population coverage, by mobile network technology",
              "value": 97.0,
              "weight": 1,
              "source": "ITU",
              "year": 2022,
              "pillar": "resilience"
            }
          ]
        },
        "defence": {
          "scores": {
            "overall": 65.68932392879802,
            "autonomy": 87.97331876700214,
            "effectiveness": 29.37790304433298,
            "sustainability": 79.71674997505893
          },
          "pillars": {
            "autonomy": {
              "scores": {
                "overall": 87.97331876700214
              }
            },
            "effectiveness": {
              "scores": {
                "overall": 29.37790304433298
              }
            },
            "sustainability": {
              "scores": {
                "overall": 79.71674997505893
              }
            }
          },
          "indicators": [
            {
              "key": "MS.MIL.XPND.CD",
              "description": "Military expenditure (current USD)",
              "value": 0.9807207892766732,
              "weight": 1,
              "source": "World Bank",
              "year": 2022,
              "pillar": "effectiveness"
            },
            {
              "key": "MS.MIL.XPND.GD.ZS",
              "description": "Military expenditure (% of GDP)",
              "value": 87.97331876700214,
              "weight": 1,
              "source": "World Bank",
              "year": 2022,
              "pillar": "autonomy"
            },
            {
              "key": "MS.MIL.XPND.PC.CD",
              "description": "Military expenditure per capita (current USD)",
              "value": 57.77508529938929,
              "weight": 1,
              "source": "Derived from World Bank",
              "year": 2022,
              "pillar": "effectiveness"
            },
            {
              "key": "MS.MIL.XPND.ZS",
              "description": "Military expenditure (% of central government expenditure)",
              "value": 79.71674997505893,
              "weight": 1,
              "source": "World Bank",
              "year": 2022,
              "pillar": "sustainability"
            }
          ]
        },
        "energy": {
          "scores": {
            "overall": 73.7042148823587,
            "autonomy": 27.50267349651871,
            "effectiveness": 100.0,
            "resilience": 93.60997115055737
          },
          "pillars": {
            "autonomy": {
              "scores": {
                "overall": 27.50267349651871
              }
            },
            "effectiveness": {
              "scores": {
                "overall": 100.0
              }
            },
            "resilience": {
              "scores": {
                "overall": 93.60997115055737
              }
            }
          },
          "indicators": [
            {
              "key": "EG.ELC.ACCS.ZS",
              "description": "Access to electricity (% of population)",
              "value": 100.0,
              "weight": 1,
              "source": "World Bank",
              "year": 2022,
              "pillar": "effectiveness"
            },
            {
              "key": "EG.ELC.LOSS.ZS",
              "description": "Electric power transmission and distribution losses (% of output)",
              "value": 93.60997115055737,
              "weight": 1,
              "source": "World Bank",
              "year": 2022,
              "pillar": "resilience"
            },
            {
              "key": "EG.IMP.CONS.ZS",
              "description": "Energy imports, net (% of energy use)",
              "value": 27.50267349651871,
              "weight": 1,
              "source": "World Bank",
              "year": 2022,
              "pillar": "autonomy"
            }
          ]
        },
        "finance": {
          "scores": {
            "overall": 44.56276629170873,
            "autonomy": 24.477500238797234,
            "effectiveness": 10.167410541911021,
            "resilience": 99.04338809441795
          },
          "pillars": {
            "autonomy": {
              "scores": {
                "overall": 24.477500238797234
              }
            },
            "effectiveness": {
              "scores": {
                "overall": 10.167410541911021
              }
            },
            "resilience": {
              "scores": {
                "overall": 99.04338809441795
              }
            }
          },
          "indicators": [
            {
              "key": "FB.AST.NPER.ZS",
              "description": "Bank nonperforming loans to total gross loans (%)",
              "value": 99.04338809441795,
              "weight": 1,
              "source": "World Bank",
              "year": 2022,
              "pillar": "resilience"
            },
            {
              "key": "FB.CBK.BRCH.P5",
              "description": "Commercial bank branches (per 100,000 adults)",
              "value": 10.167410541911021,
              "weight": 1,
              "source": "World Bank",
              "year": 2022,
              "pillar": "effectiveness"
            },
            {
              "key": "FS.AST.PRVT.GD.ZS",
              "description": "Domestic credit to private sector (% of GDP)",
              "value": 24.477500238797234,
              "weight": 1,
              "source": "World Bank",
              "year": 2022,
              "pillar": "autonomy"
            }
          ]
        },
        "general": {
          "scores": {
            "overall": 0.11726601718870001,
            "context": 0.11726601718870001
          },
          "pillars": {
            "context": {
              "scores": {
                "overall": 0.11726601718870001
              }
            }
          },
          "indicators": [
            {
              "key": "SP.POP.TOTL",
              "description": "Population, total",
              "value": 0.11726601718870001,
              "weight": 1,
              "source": "World Bank",
              "year": 2022,
              "pillar": "context"
            }
          ]
        },
        "healthcare": {
          "scores": {
            "overall": 57.12680549019391,
            "autonomy": 38.4873949579832,
            "effectiveness": 98.98989898989899,
            "sustainability": 33.903122522699555
          },
          "pillars": {
            "autonomy": {
              "scores": {
                "overall": 38.4873949579832
              }
            },
            "effectiveness": {
              "scores": {
                "overall": 98.98989898989899
              }
            },
            "sustainability": {
              "scores": {
                "overall": 33.903122522699555
              }
            }
          },
          "indicators": [
            {
              "key": "HWF_0001",
              "description": "Physicians per 1,000 population",
              "value": 38.4873949579832,
              "weight": 1,
              "source": "WHO",
              "year": 2022,
              "pillar": "autonomy"
            },
            {
              "key": "SH.IMM.IDPT",
              "description": "Immunization, DPT (% of children ages 12-23 months)",
              "value": 98.98989898989899,
              "weight": 1,
              "source": "World Bank",
              "year": 2022,
              "pillar": "effectiveness"
            },
            {
              "key": "SH.XPD.CHEX.PC.CD",
              "description": "Current health expenditure per capita (current US$)",
              "value": 33.903122522699555,
              "weight": 1,
              "source": "World Bank",
              "year": 2022,
              "pillar": "sustainability"
            }
          ]
        },
        "information_technology": {
          "scores": {
            "overall": 67.8188176340492,
            "autonomy": 57.56956052432364,
            "effectiveness": 45.88689237782395,
            "sustainability": 100.0
          },
          "pillars": {
            "autonomy": {
              "scores": {
                "overall": 57.56956052432364
              }
            },
            "effectiveness": {
              "scores": {
                "overall": 45.88689237782395
              }
            },
            "sustainability": {
              "scores": {
                "overall": 100.0
              }
            }
          },
          "indicators": [
            {
              "key": "BX.GSR.CCIS.ZS",
              "description": "ICT service exports (% of service exports, BoP)",
              "value": 84.69603103747284,
              "weight": 1,
              "source": "World Bank",
              "year": 2022,
              "pillar": "autonomy"
            },
            {
              "key": "GB.XPD.RSDV.GD.ZS",
              "description": "Research and development expenditure (% of GDP)",
              "value": 100.0,
              "weight": 1,
              "source": "World Bank",
              "year": 2022,
              "pillar": "sustainability"
            },
            {
              "key": "IT.NET.SECR.P6",
              "description": "Secure Internet servers (per 1 million people)",
              "value": 0.39998283871498247,
              "weight": 1,
              "source": "World Bank",
              "year": 2022,
              "pillar": "effectiveness"
            },
            {
              "key": "IT.NET.USER.ZS",
              "description": "Individuals using the Internet (% of population)",
              "value": 91.37380191693292,
              "weight": 1,
              "source": "World Bank",
              "year": 2022,
              "pillar": "effectiveness"
            },
            {
              "key": "TX.VAL.TECH.MF.ZS",
              "description": "High-technology exports (% of manufactured exports)",
              "value": 30.443090011174444,
              "weight": 1,
              "source": "World Bank",
              "year": 2022,
              "pillar": "autonomy"
            }
          ]
        },
        "transport": {
          "scores": {
            "overall": 77.8361955533818,
            "autonomy": 85.4025260540848,
            "effectiveness": 77.27272727272727,
            "resilience": 70.83333333333334
          },
          "pillars": {
            "autonomy": {
              "scores": {
                "overall": 85.4025260540848
              }
            },
            "effectiveness": {
              "scores": {
                "overall": 77.27272727272727
              }
            },
            "resilience": {
              "scores": {
                "overall": 70.83333333333334
              }
            }
          },
          "indicators": [
            {
              "key": "EG.USE.PCAP.KG.OE",
              "description": "Energy use (kg of oil equivalent per capita)",
              "value": 85.4025260540848,
              "weight": 1,
              "source": "World Bank",
              "year": 2022,
              "pillar": "autonomy"
            },
            {
              "key": "LP.LPI.OVRL.XQ",
              "description": "Logistics performance index: Overall",
              "value": 70.83333333333334,
              "weight": 1,
              "source": "World Bank",
              "year": 2022,
              "pillar": "resilience"
            },
            {
              "key": "LP.LPI.TIME.XQ",
              "description": "Logistics performance index: Timeliness of shipments",
              "value": 77.27272727272727,
              "weight": 1,
              "source": "World Bank",
              "year": 2022,
              "pillar": "effectiveness"
            }
          ]
        },
        "water": {
          "scores": {
            "overall": 97.91101618611043,
            "effectiveness": 96.44426,
            "resilience": 99.37777237222085
          },
          "pillars": {
            "effectiveness": {
              "scores": {
                "overall": 96.44426
              }
            },
            "resilience": {
              "scores": {
                "overall": 99.37777237222085
              }
            }
          },
          "indicators": [
            {
              "key": "WSH_SANITATION_SAFELY_MANAGED",
              "description": "Population with access to safely managed sanitation services (%)",
              "value": 96.44426,
              "weight": 1,
              "source": "WHO",
              "year": 2022,
              "pillar": "effectiveness"
            },
            {
              "key": "WSH_WATER_SAFELY_MANAGED",
              "description": "Population with access to safely managed drinking water (%)",
              "value": 99.37777237222085,
              "weight": 1,
              "source": "WHO",
              "year": 2022,
              "pillar": "resilience"
            }
          ]
        }
      }
    },
    {
      "scores": {
        "overall": 57.31401114254029,
        "resilience": 98.6168918198394,
        "sustainability": 75.53512819596443,
        "autonomy": 85.758285991999,
        "effectiveness": 43.27581653017669,
        "context": 0.12084619803462687
      },
      "industries": {
        "communications": {
          "scores": {
            "overall": 67.92958189933425,
            "resilience": 97.0,
            "sustainability": 38.859163798668504
          },
          "pillars": {
            "resilience": {
              "scores": {
                "overall": 97.0
              }
            },
            "sustainability": {
              "scores": {
                "overall": 38.859163798668504
              }
            }
          },
          "indicators": [
            {
              "key": "IT.NET.BBND.P2",
              "description": "Fixed-broadband subscriptions (per 100 people)",
              "value": 38.859163798668504,
              "weight": 1,
              "source": "World Bank",
              "year": 2023,
              "pillar": "sustainability"
            },
            {
              "key": "ITU_MOB_BB_COVERAGE",
              "description": "Population coverage, by mobile network technology",
              "value": 97.0,
              "weight": 1,
              "source": "ITU",
              "year": 2023,
              "pillar": "resilience"
            }
          ]
        },
        "defence": {
          "scores": {
            "overall": 62.553474886321204,
            "autonomy": 85.61896164606873,
            "effectiveness": 26.506334816930448,
            "sustainability": 75.53512819596443
          },
          "pillars": {
            "autonomy": {
              "scores": {
                "overall": 85.61896164606873
              }
            },
            "effectiveness": {
              "scores": {
                "overall": 26.506334816930448
              }
            },
            "sustainability": {
              "scores": {
                "overall": 75.53512819596443
              }
            }
          },
          "indicators": [
            {
              "key": "MS.MIL.XPND.CD",
              "description": "Military expenditure (current USD)",
              "value": 1.1521956772184327,
              "weight": 1,
              "source": "World Bank",
              "year": 2023,
              "pillar": "effectiveness"
            },
            {
              "key": "MS.MIL.XPND.GD.ZS",
              "description": "Military expenditure (% of GDP)",
              "value": 85.61896164606873,
              "weight": 1,
              "source": "World Bank",
              "year": 2023,
              "pillar": "autonomy"
            },
            {
              "key": "MS.MIL.XPND.PC.CD",
              "description": "Military expenditure per capita (current USD)",
              "value": 51.860473956642466,
              "weight": 1,
              "source": "Derived from World Bank",
              "year": 2023,
              "pillar": "effectiveness"
            },
            {
              "key": "MS.MIL.XPND.ZS",
              "description": "Military expenditure (% of central government expenditure)",
              "value": 75.53512819596443,
              "weight": 1,
              "source": "World Bank",
              "year": 2023,
              "pillar": "sustainability"
            }
          ]
        },
        "energy": {
          "scores": {
            "overall": 73.9741463466814,
            "autonomy": 28.320958963384925,
            "effectiveness": 100.0,
            "resilience": 93.60148007665929
          },
          "pillars": {
            "autonomy": {
              "scores": {
                "overall": 28.320958963384925
              }
            },
            "effectiveness": {
              "scores": {
                "overall": 100.0
              }
            },
            "resilience": {
              "scores": {
                "overall": 93.60148007665929
              }
            }
          },
          "indicators": [
            {
              "key": "EG.ELC.ACCS.ZS",
              "description": "Access to electricity (% of population)",
              "value": 100.0,
              "weight": 1,
              "source": "World Bank",
              "year": 2023,
              "pillar": "effectiveness"
            },
            {
              "key": "EG.ELC.LOSS.ZS",
              "description": "Electric power transmission and distribution losses (% of output)",
              "value": 93.60148007665929,
              "weight": 1,
              "source": "World Bank",
              "year": 2023,
              "pillar": "resilience"
            },
            {
              "key": "EG.IMP.CONS.ZS",
              "description": "Energy imports, net (% of energy use)",
              "value": 28.320958963384925,
              "weight": 1,
              "source": "World Bank",
              "year": 2023,
              "pillar": "autonomy"
            }
          ]
        },
        "finance": {
          "scores": {
            "overall": 44.27856209145966,
            "autonomy": 24.27244148067284,
            "effectiveness": 9.946352973866755,
            "resilience": 98.6168918198394
          },
          "pillars": {
            "autonomy": {
              "scores": {
                "overall": 24.27244148067284
              }
            },
            "effectiveness": {
              "scores": {
                "overall": 9.946352973866755
              }
            },
            "resilience": {
              "scores": {
                "overall": 98.6168918198394
              }
            }
          },
          "indicators": [
            {
              "key": "FB.AST.NPER.ZS",
              "description": "Bank nonperforming loans to total gross loans (%)",
              "value": 98.6168918198394,
              "weight": 1,
              "source": "World Bank",
              "year": 2023,
              "pillar": "resilience"
            },
            {
              "key": "FB.CBK.BRCH.P5",
              "description": "Commercial bank branches (per 100,000 adults)",
              "value": 9.946352973866755,
              "weight": 1,
              "source": "World Bank",
              "year": 2023,
              "pillar": "effectiveness"
            },
            {
              "key": "FS.AST.PRVT.GD.ZS",
              "description": "Domestic credit to private sector (% of GDP)",
              "value": 24.27244148067284,
              "weight": 1,
              "source": "World Bank",
              "year": 2023,
              "pillar": "autonomy"
            }
          ]
        },
        "general": {
          "scores": {
            "overall": 0.12084619803462687,
            "context": 0.12084619803462687
          },
          "pillars": {
            "context": {
              "scores": {
                "overall": 0.12084619803462687
              }
            }
          },
          "indicators": [
            {
              "key": "SP.POP.TOTL",
              "description": "Population, total",
              "value": 0.12084619803462687,
              "weight": 1,
              "source": "World Bank",
              "year": 2023,
              "pillar": "context"
            }
          ]
        },
        "healthcare": {
          "scores": {
            "overall": 69.3216301672184,
            "autonomy": 39.653361344537814,
            "effectiveness": 98.98989898989899
          },
          "pillars": {
            "autonomy": {
              "scores": {
                "overall": 39.653361344537814
              }
            },
            "effectiveness": {
              "scores": {
                "overall": 98.98989898989899
              }
            }
          },
          "indicators": [
            {
              "key": "HWF_0001",
              "description": "Physicians per 1,000 population",
              "value": 39.653361344537814,
              "weight": 1,
              "source": "WHO",
              "year": 2023,
              "pillar": "autonomy"
            },
            {
              "key": "SH.IMM.IDPT",
              "description": "Immunization, DPT (% of children ages 12-23 months)",
              "value": 98.98989898989899,
              "weight": 1,
              "source": "World Bank",
              "year": 2023,
              "pillar": "effectiveness"
            }
          ]
        },
        "information_technology": {
          "scores": {
            "overall": 54.57556155927375,
            "autonomy": 65.87530658837082,
            "effectiveness": 43.27581653017669
          },
          "pillars": {
            "autonomy": {
              "scores": {
                "overall": 65.87530658837082
              }
            },
            "effectiveness": {
              "scores": {
                "overall": 43.27581653017669
              }
            }
          },
          "indicators": [
            {
              "key": "BX.GSR.CCIS.ZS",
              "description": "ICT service exports (% of service exports, BoP)",
              "value": 95.30988731750443,
              "weight": 1,
              "source": "World Bank",
              "year": 2023,
              "pillar": "autonomy"
            },
            {
              "key": "IT.NET.SECR.P6",
              "description": "Secure Internet servers (per 1 million people)",
              "value": 0.3961485023129172,
              "weight": 1,
              "source": "World Bank",
              "year": 2023,
              "pillar": "effectiveness"
            },
            {
              "key": "IT.NET.USER.ZS",
              "description": "Individuals using the Internet (% of population)",
              "value": 86.15548455804047,
              "weight": 1,
              "source": "World Bank",
              "year": 2023,
              "pillar": "effectiveness"
            },
            {
              "key": "TX.VAL.TECH.MF.ZS",
              "description": "High-technology exports (% of manufactured exports)",
              "value": 36.44072585923722,
              "weight": 1,
              "source": "World Bank",
              "year": 2023,
              "pillar": "autonomy"
            }
          ]
        },
        "transport": {
          "scores": {
            "overall": 85.758285991999,
            "autonomy": 85.758285991999
          },
          "pillars": {
            "autonomy": {
              "scores": {
                "overall": 85.758285991999
              }
            }
          },
          "indicators": [
            {
              "key": "EG.USE.PCAP.KG.OE",
              "description": "Energy use (kg of oil equivalent per capita)",
              "value": 85.758285991999,
              "weight": 1,
              "source": "World Bank",
              "year": 2023,
              "pillar": "autonomy"
            }
          ]
        }
      }
    },
    {
      "scores": {
        "overall": 17.53166803070917,
        "context": 0.1223863513041954,
        "autonomy": 69.50328398007983,
        "effectiveness": 0.3786154401484682
      },
      "industries": {
        "general": {
          "scores": {
            "overall": 0.1223863513041954,
            "context": 0.1223863513041954
          },
          "pillars": {
            "context": {
              "scores": {
                "overall": 0.1223863513041954
              }
            }
          },
          "indicators": [
            {
              "key": "SP.POP.TOTL",
              "description": "Population, total",
              "value": 0.1223863513041954,
              "weight": 1,
              "source": "World Bank",
              "year": 2024,
              "pillar": "context"
            }
          ]
        },
        "information_technology": {
          "scores": {
            "overall": 34.94094971011415,
            "autonomy": 69.50328398007983,
            "effectiveness": 0.3786154401484682
          },
          "pillars": {
            "autonomy": {
              "scores": {
                "overall": 69.50328398007983
              }
            },
            "effectiveness": {
              "scores": {
                "overall": 0.3786154401484682
              }
            }
          },
          "indicators": [
            {
              "key": "BX.GSR.CCIS.ZS",
              "description": "ICT service exports (% of service exports, BoP)",
              "value": 100.0,
              "weight": 1,
              "source": "World Bank",
              "year": 2024,
              "pillar": "autonomy"
            },
            {
              "key": "IT.NET.SECR.P6",
              "description": "Secure Internet servers (per 1 million people)",
              "value": 0.3786154401484682,
              "weight": 1,
              "source": "World Bank",
              "year": 2024,
              "pillar": "effectiveness"
            },
            {
              "key": "TX.VAL.TECH.MF.ZS",
              "description": "High-technology exports (% of manufactured exports)",
              "value": 39.00656796015964,
              "weight": 1,
              "source": "World Bank",
              "year": 2024,
              "pillar": "autonomy"
            }
          ]
        }
      }
    }
  ]
}